{
  "all_candidates": [
    {
      "topic": "Should social media platforms be more accountable for harmful content?",
      "news_anchor": "On July 7 and 9, 2026, Meta and Instagram faced criticism and government notices over the presence of child sexual abuse material (CSAM) and related advertisements on their platforms in India.",
      "relatability": 9,
      "opinion_strength": 10,
      "comment_potential": 10,
      "discussion_potential": 10,
      "shareability": 10,
      "trend_momentum": 10,
      "brand_safety": 5,
      "total_score": 9.87
    },
    {
      "topic": "Should all national exams revert to pen-and-paper format?",
      "news_anchor": "The successful NEET 2026 re-exam on June 21, 2026, still highlighted flaws in the system, with calls to return to pen-and-paper tests.",
      "relatability": 9,
      "opinion_strength": 9,
      "comment_potential": 10,
      "discussion_potential": 10,
      "shareability": 9,
      "trend_momentum": 9,
      "brand_safety": 7,
      "total_score": 9.4
    },
    {
      "topic": "Should exam deadlines be more flexible for students?",
      "news_anchor": "On June 22, 2026, many students were denied entry to the NEET-UG re-examination due to reaching centers late or biometric issues.",
      "relatability": 9,
      "opinion_strength": 9,
      "comment_potential": 10,
      "discussion_potential": 9,
      "shareability": 9,
      "trend_momentum": 9,
      "brand_safety": 7,
      "total_score": 9.22
    },
    {
      "topic": "Should consumers have a choice of non-E20 petrol?",
      "news_anchor": "On July 10, 2026, the petroleum ministry defended the E20 ethanol-blending program but faced consumer concerns over the absence of pure petrol or E10 at pumps.",
      "relatability": 9,
      "opinion_strength": 9,
      "comment_potential": 9,
      "discussion_potential": 9,
      "shareability": 8,
      "trend_momentum": 10,
      "brand_safety": 9,
      "total_score": 9.15
    },
    {
      "topic": "Should E20 petrol be clearly labelled at pumps?",
      "news_anchor": "The government acknowledged on July 10, 2026, that E20 petrol can reduce fuel economy by 3-5% and is costlier to produce at current crude prices, amid consumer backlash.",
      "relatability": 9,
      "opinion_strength": 8,
      "comment_potential": 9,
      "discussion_potential": 9,
      "shareability": 8,
      "trend_momentum": 10,
      "brand_safety": 9,
      "total_score": 9.03
    },
    {
      "topic": "Are AI-driven tech layoffs justifiable for productivity gains?",
      "news_anchor": "Reports on July 9, 2026, indicate that up to 35,000 tech jobs may be eliminated this year in India, with AI adoption being a primary driver for workforce restructuring.",
      "relatability": 8,
      "opinion_strength": 8,
      "comment_potential": 9,
      "discussion_potential": 9,
      "shareability": 9,
      "trend_momentum": 10,
      "brand_safety": 8,
      "total_score": 9.0
    },
    {
      "topic": "Should government mandate work-from-home during peak pollution?",
      "news_anchor": "Delhi's new EV Policy, effective July 1, 2026, includes a 50% work-from-home mandate for certain periods to curb pollution.",
      "relatability": 8,
      "opinion_strength": 8,
      "comment_potential": 9,
      "discussion_potential": 9,
      "shareability": 9,
      "trend_momentum": 9,
      "brand_safety": 8,
      "total_score": 8.75
    },
    {
      "topic": "Should merchants bear UPI interchange fees for higher transactions?",
      "news_anchor": "Updated UPI regulations for 2026 include interchange fees for wallet-based merchant payments above \u20b92,000, payable by merchants, to ensure ecosystem sustainability.",
      "relatability": 8,
      "opinion_strength": 8,
      "comment_potential": 9,
      "discussion_potential": 9,
      "shareability": 8,
      "trend_momentum": 9,
      "brand_safety": 9,
      "total_score": 8.65
    },
    {
      "topic": "Is Delhi's EV Policy 2.0 fair to fossil fuel vehicle owners?",
      "news_anchor": "Delhi's EV Policy 2.0, effective July 1, 2026, proposes gradually restricting registrations of selected petrol, diesel, and CNG vehicles.",
      "relatability": 8,
      "opinion_strength": 8,
      "comment_potential": 9,
      "discussion_potential": 9,
      "shareability": 8,
      "trend_momentum": 9,
      "brand_safety": 8,
      "total_score": 8.65
    },
    {
      "topic": "Is new UPI two-factor authentication beneficial for users?",
      "news_anchor": "From April 1, 2026, new UPI rules require a second verification layer (OTP, biometric, or device-based approval) for transactions to enhance security.",
      "relatability": 9,
      "opinion_strength": 7,
      "comment_potential": 8,
      "discussion_potential": 8,
      "shareability": 7,
      "trend_momentum": 9,
      "brand_safety": 9,
      "total_score": 8.16
    },
    {
      "topic": "Should tech companies openly announce AI-related job cuts?",
      "news_anchor": "A report from July 9, 2026, highlighted that many Indian IT companies are implementing 'silent layoffs' through performance reviews, rather than formal announcements, due to AI integration.",
      "relatability": 8,
      "opinion_strength": 7,
      "comment_potential": 8,
      "discussion_potential": 8,
      "shareability": 8,
      "trend_momentum": 9,
      "brand_safety": 8,
      "total_score": 8.13
    },
    {
      "topic": "Should FCRA 2.0 increase scrutiny on foreign NGO funding?",
      "news_anchor": "On July 1, 2026, Union Home Minister Amit Shah launched FCRA 2.0, introducing stricter oversight and new rules for NGOs receiving foreign donations.",
      "relatability": 7,
      "opinion_strength": 7,
      "comment_potential": 8,
      "discussion_potential": 8,
      "shareability": 7,
      "trend_momentum": 8,
      "brand_safety": 7,
      "total_score": 7.65
    },
    {
      "topic": "Are revised wage rates for unskilled workers adequate?",
      "news_anchor": "On June 30, 2026, the Ministry of Rural Development notified revised State-wise wage rates for unskilled manual workers under the VB-G RAM G Act, 2025, effective July 1, 2026.",
      "relatability": 7,
      "opinion_strength": 8,
      "comment_potential": 8,
      "discussion_potential": 8,
      "shareability": 7,
      "trend_momentum": 7,
      "brand_safety": 8,
      "total_score": 7.52
    },
    {
      "topic": "Should states set minimum wages under new Code on Wages Rules?",
      "news_anchor": "On June 30, 2026, the Bihar Government notified the Code on Wages (Bihar) Rules, 2026, laying down a framework for minimum wages, effective July 1, 2026.",
      "relatability": 7,
      "opinion_strength": 7,
      "comment_potential": 8,
      "discussion_potential": 8,
      "shareability": 7,
      "trend_momentum": 7,
      "brand_safety": 8,
      "total_score": 7.4
    },
    {
      "topic": "Should UPI apps limit balance enquiry requests?",
      "news_anchor": "Recent UPI operational changes, effective July 8, 2026, include limits on balance enquiry and linked account refresh requests per app to reduce system load.",
      "relatability": 8,
      "opinion_strength": 6,
      "comment_potential": 7,
      "discussion_potential": 7,
      "shareability": 6,
      "trend_momentum": 8,
      "brand_safety": 9,
      "total_score": 7.16
    },
    {
      "topic": "Should UPI AutoPay mandates process only during non-peak hours?",
      "news_anchor": "UPI operational guidelines updated around July 8, 2026, state that AutoPay mandates are processed only during designated non-peak hours to improve system efficiency.",
      "relatability": 7,
      "opinion_strength": 6,
      "comment_potential": 7,
      "discussion_potential": 7,
      "shareability": 6,
      "trend_momentum": 8,
      "brand_safety": 9,
      "total_score": 7.03
    },
    {
      "topic": "Should public transport integrate more electric feeder services?",
      "news_anchor": "Delhi's EV Policy 2.0, effective July 1, 2026, emphasizes better integration between public transport and electric feeder services for first and last-mile connectivity.",
      "relatability": 7,
      "opinion_strength": 6,
      "comment_potential": 7,
      "discussion_potential": 7,
      "shareability": 6,
      "trend_momentum": 8,
      "brand_safety": 9,
      "total_score": 7.03
    },
    {
      "topic": "Is deferring e-invoice reporting a positive step?",
      "news_anchor": "On July 10, 2026, the GST department deferred the 7-day time limit to report old e-invoices by three months.",
      "relatability": 6,
      "opinion_strength": 6,
      "comment_potential": 6,
      "discussion_potential": 6,
      "shareability": 5,
      "trend_momentum": 7,
      "brand_safety": 9,
      "total_score": 6.15
    },
    {
      "topic": "Is extending GSTAT appeals deadline beneficial for taxpayers?",
      "news_anchor": "The central government extended the last date for filing GSTAT appeals until July 31, 2026, as announced around July 2, 2026.",
      "relatability": 6,
      "opinion_strength": 5,
      "comment_potential": 6,
      "discussion_potential": 6,
      "shareability": 5,
      "trend_momentum": 6,
      "brand_safety": 9,
      "total_score": 5.78
    },
    {
      "topic": "Should GSTN revise annual turnover amendment timelines?",
      "news_anchor": "GSTN revised the timeline for Aggregate Annual Turnover (AATO) Amendments, effective July 1, 2026.",
      "relatability": 6,
      "opinion_strength": 5,
      "comment_potential": 6,
      "discussion_potential": 6,
      "shareability": 5,
      "trend_momentum": 6,
      "brand_safety": 9,
      "total_score": 5.78
    }
  ],
  "eligible_candidates": [
    {
      "topic": "Should consumers have a choice of non-E20 petrol?",
      "news_anchor": "On July 10, 2026, the petroleum ministry defended the E20 ethanol-blending program but faced consumer concerns over the absence of pure petrol or E10 at pumps.",
      "relatability": 9,
      "opinion_strength": 9,
      "comment_potential": 9,
      "discussion_potential": 9,
      "shareability": 8,
      "trend_momentum": 10,
      "brand_safety": 9,
      "total_score": 9.15
    },
    {
      "topic": "Should E20 petrol be clearly labelled at pumps?",
      "news_anchor": "The government acknowledged on July 10, 2026, that E20 petrol can reduce fuel economy by 3-5% and is costlier to produce at current crude prices, amid consumer backlash.",
      "relatability": 9,
      "opinion_strength": 8,
      "comment_potential": 9,
      "discussion_potential": 9,
      "shareability": 8,
      "trend_momentum": 10,
      "brand_safety": 9,
      "total_score": 9.03
    },
    {
      "topic": "Are AI-driven tech layoffs justifiable for productivity gains?",
      "news_anchor": "Reports on July 9, 2026, indicate that up to 35,000 tech jobs may be eliminated this year in India, with AI adoption being a primary driver for workforce restructuring.",
      "relatability": 8,
      "opinion_strength": 8,
      "comment_potential": 9,
      "discussion_potential": 9,
      "shareability": 9,
      "trend_momentum": 10,
      "brand_safety": 8,
      "total_score": 9.0
    },
    {
      "topic": "Should government mandate work-from-home during peak pollution?",
      "news_anchor": "Delhi's new EV Policy, effective July 1, 2026, includes a 50% work-from-home mandate for certain periods to curb pollution.",
      "relatability": 8,
      "opinion_strength": 8,
      "comment_potential": 9,
      "discussion_potential": 9,
      "shareability": 9,
      "trend_momentum": 9,
      "brand_safety": 8,
      "total_score": 8.75
    },
    {
      "topic": "Should merchants bear UPI interchange fees for higher transactions?",
      "news_anchor": "Updated UPI regulations for 2026 include interchange fees for wallet-based merchant payments above \u20b92,000, payable by merchants, to ensure ecosystem sustainability.",
      "relatability": 8,
      "opinion_strength": 8,
      "comment_potential": 9,
      "discussion_potential": 9,
      "shareability": 8,
      "trend_momentum": 9,
      "brand_safety": 9,
      "total_score": 8.65
    },
    {
      "topic": "Is Delhi's EV Policy 2.0 fair to fossil fuel vehicle owners?",
      "news_anchor": "Delhi's EV Policy 2.0, effective July 1, 2026, proposes gradually restricting registrations of selected petrol, diesel, and CNG vehicles.",
      "relatability": 8,
      "opinion_strength": 8,
      "comment_potential": 9,
      "discussion_potential": 9,
      "shareability": 8,
      "trend_momentum": 9,
      "brand_safety": 8,
      "total_score": 8.65
    },
    {
      "topic": "Is new UPI two-factor authentication beneficial for users?",
      "news_anchor": "From April 1, 2026, new UPI rules require a second verification layer (OTP, biometric, or device-based approval) for transactions to enhance security.",
      "relatability": 9,
      "opinion_strength": 7,
      "comment_potential": 8,
      "discussion_potential": 8,
      "shareability": 7,
      "trend_momentum": 9,
      "brand_safety": 9,
      "total_score": 8.16
    },
    {
      "topic": "Should tech companies openly announce AI-related job cuts?",
      "news_anchor": "A report from July 9, 2026, highlighted that many Indian IT companies are implementing 'silent layoffs' through performance reviews, rather than formal announcements, due to AI integration.",
      "relatability": 8,
      "opinion_strength": 7,
      "comment_potential": 8,
      "discussion_potential": 8,
      "shareability": 8,
      "trend_momentum": 9,
      "brand_safety": 8,
      "total_score": 8.13
    },
    {
      "topic": "Are revised wage rates for unskilled workers adequate?",
      "news_anchor": "On June 30, 2026, the Ministry of Rural Development notified revised State-wise wage rates for unskilled manual workers under the VB-G RAM G Act, 2025, effective July 1, 2026.",
      "relatability": 7,
      "opinion_strength": 8,
      "comment_potential": 8,
      "discussion_potential": 8,
      "shareability": 7,
      "trend_momentum": 7,
      "brand_safety": 8,
      "total_score": 7.52
    },
    {
      "topic": "Should states set minimum wages under new Code on Wages Rules?",
      "news_anchor": "On June 30, 2026, the Bihar Government notified the Code on Wages (Bihar) Rules, 2026, laying down a framework for minimum wages, effective July 1, 2026.",
      "relatability": 7,
      "opinion_strength": 7,
      "comment_potential": 8,
      "discussion_potential": 8,
      "shareability": 7,
      "trend_momentum": 7,
      "brand_safety": 8,
      "total_score": 7.4
    },
    {
      "topic": "Should UPI apps limit balance enquiry requests?",
      "news_anchor": "Recent UPI operational changes, effective July 8, 2026, include limits on balance enquiry and linked account refresh requests per app to reduce system load.",
      "relatability": 8,
      "opinion_strength": 6,
      "comment_potential": 7,
      "discussion_potential": 7,
      "shareability": 6,
      "trend_momentum": 8,
      "brand_safety": 9,
      "total_score": 7.16
    },
    {
      "topic": "Should UPI AutoPay mandates process only during non-peak hours?",
      "news_anchor": "UPI operational guidelines updated around July 8, 2026, state that AutoPay mandates are processed only during designated non-peak hours to improve system efficiency.",
      "relatability": 7,
      "opinion_strength": 6,
      "comment_potential": 7,
      "discussion_potential": 7,
      "shareability": 6,
      "trend_momentum": 8,
      "brand_safety": 9,
      "total_score": 7.03
    },
    {
      "topic": "Should public transport integrate more electric feeder services?",
      "news_anchor": "Delhi's EV Policy 2.0, effective July 1, 2026, emphasizes better integration between public transport and electric feeder services for first and last-mile connectivity.",
      "relatability": 7,
      "opinion_strength": 6,
      "comment_potential": 7,
      "discussion_potential": 7,
      "shareability": 6,
      "trend_momentum": 8,
      "brand_safety": 9,
      "total_score": 7.03
    },
    {
      "topic": "Is deferring e-invoice reporting a positive step?",
      "news_anchor": "On July 10, 2026, the GST department deferred the 7-day time limit to report old e-invoices by three months.",
      "relatability": 6,
      "opinion_strength": 6,
      "comment_potential": 6,
      "discussion_potential": 6,
      "shareability": 5,
      "trend_momentum": 7,
      "brand_safety": 9,
      "total_score": 6.15
    },
    {
      "topic": "Is extending GSTAT appeals deadline beneficial for taxpayers?",
      "news_anchor": "The central government extended the last date for filing GSTAT appeals until July 31, 2026, as announced around July 2, 2026.",
      "relatability": 6,
      "opinion_strength": 5,
      "comment_potential": 6,
      "discussion_potential": 6,
      "shareability": 5,
      "trend_momentum": 6,
      "brand_safety": 9,
      "total_score": 5.78
    },
    {
      "topic": "Should GSTN revise annual turnover amendment timelines?",
      "news_anchor": "GSTN revised the timeline for Aggregate Annual Turnover (AATO) Amendments, effective July 1, 2026.",
      "relatability": 6,
      "opinion_strength": 5,
      "comment_potential": 6,
      "discussion_potential": 6,
      "shareability": 5,
      "trend_momentum": 6,
      "brand_safety": 9,
      "total_score": 5.78
    }
  ],
  "winner": {
    "topic": "Should consumers have a choice of non-E20 petrol?",
    "news_anchor": "On July 10, 2026, the petroleum ministry defended the E20 ethanol-blending program but faced consumer concerns over the absence of pure petrol or E10 at pumps.",
    "relatability": 9,
    "opinion_strength": 9,
    "comment_potential": 9,
    "discussion_potential": 9,
    "shareability": 8,
    "trend_momentum": 10,
    "brand_safety": 9,
    "total_score": 9.15
  }
}